mango_genetic/__init__.py
mango_genetic/const.py
mango_genetic/config/__init__.py
mango_genetic/config/config.py
mango_genetic/individual/__init__.py
mango_genetic/individual/base_individual.py
mango_genetic/population/__init__.py
mango_genetic/population/base_population.py
mango_genetic/problem/__init__.py
mango_genetic/problem/base_problem.py
mango_genetic/shared/__init__.py
mango_genetic/shared/exceptions.py
mango_genetic/tests/__init__.py
mango_genetic/tests/const.py
mango_genetic/tests/test_genetic.py
mango_genetic/tests/data/test_ackley.cfg
mango_genetic/tests/data/test_bukin.cfg
mango_genetic/tests/data/test_cross_in_tray.cfg
mango_genetic/tests/data/test_custom_problem.cfg
mango_genetic/tests/data/test_inverted_griewank_10d.cfg
mango_genetic/tests/data/test_levy.cfg
mango_genetic/tests/data/test_rastrigin.cfg
mango_genetic/tests/data/test_schwefel.cfg
mango_genetic-1.0.2.dist-info/licenses/LICENSE
mango_genetic-1.0.2.dist-info/METADATA
mango_genetic-1.0.2.dist-info/WHEEL
mango_genetic-1.0.2.dist-info/top_level.txt
mango_genetic-1.0.2.dist-info/RECORD
